spotifycurator/__init__.py
spotifycurator/spotifycurator.py
spotifycurator-0.1.1.dist-info/LICENSE.md
spotifycurator-0.1.1.dist-info/METADATA
spotifycurator-0.1.1.dist-info/WHEEL
spotifycurator-0.1.1.dist-info/entry_points.txt
spotifycurator-0.1.1.dist-info/top_level.txt
spotifycurator-0.1.1.dist-info/RECORD
